[{"model": "scenarios.expansion", "pk": 1, "fields": {"name": "Memoir '44", "abbreviation": "M44"}}, {"model": "scenarios.expansion", "pk": 2, "fields": {"name": "Air Pack", "abbreviation": "AIR"}}, {"model": "scenarios.expansion", "pk": 3, "fields": {"name": "Battle Maps Series 2", "abbreviation": "BM2"}}, {"model": "scenarios.subexpansion", "pk": 1, "fields": {"name": "The Battles of Khalkin Gol", "abbreviation": "BoKG", "parent": ["BM2"]}}, {"model": "scenarios.scenario", "pk": 1, "fields": {"name": "Pegasus Bridge", "expansion": ["M44"], "sub_expansion": null, "number": "1", "board": "1", "scenario_type": "1", "date": " June 6th 1944"}}, {"model": "scenarios.scenario", "pk": 2, "fields": {"name": "Encirclement at Khalkin Gol", "expansion": ["BM2"], "sub_expansion": ["BoKG"], "number": "4373", "board": "1", "scenario_type": "2", "date": " September 15th 1939"}}]